busy_agent/__init__.py
busy_agent/agent.py
busy_agent/cli.py
busy_agent/data/config.json
busy_agent/data/datasets/react-llama.parquet
busy_agent-0.1.3.dist-info/LICENSE
busy_agent-0.1.3.dist-info/METADATA
busy_agent-0.1.3.dist-info/WHEEL
busy_agent-0.1.3.dist-info/entry_points.txt
busy_agent-0.1.3.dist-info/top_level.txt
busy_agent-0.1.3.dist-info/RECORD
