Metadata-Version: 2.1
Name: busy-agent
Version: 0.1.3
Summary: 模拟 ReAct Agent 工作过程 - Simulate ReAct Agent working process
Home-page: https://github.com/demouo/busy-agent
Author: Busy Agent Contributors
Author-email: 
Project-URL: Bug Reports, https://github.com/demouo/busy-agent/issues
Project-URL: Source, https://github.com/demouo/busy-agent
Keywords: agent react llm simulation
Classifier: Development Status :: 3 - Alpha
Classifier: Intended Audience :: Developers
Classifier: Topic :: Software Development :: Libraries :: Python Modules
Classifier: License :: OSI Approved :: MIT License
Classifier: Programming Language :: Python :: 3
Classifier: Programming Language :: Python :: 3.7
Classifier: Programming Language :: Python :: 3.8
Classifier: Programming Language :: Python :: 3.9
Classifier: Programming Language :: Python :: 3.10
Classifier: Programming Language :: Python :: 3.11
Requires-Python: >=3.7
License-File: LICENSE
Requires-Dist: pandas
Requires-Dist: pyarrow
